[
  {
    "name": "1.webp",
    "src": "stickers/KUNgal4/1.webp"
  },
  {
    "name": "10.webp",
    "src": "stickers/KUNgal4/10.webp"
  },
  {
    "name": "11.webp",
    "src": "stickers/KUNgal4/11.webp"
  },
  {
    "name": "12.webp",
    "src": "stickers/KUNgal4/12.webp"
  },
  {
    "name": "13.webp",
    "src": "stickers/KUNgal4/13.webp"
  },
  {
    "name": "14.webp",
    "src": "stickers/KUNgal4/14.webp"
  },
  {
    "name": "15.webp",
    "src": "stickers/KUNgal4/15.webp"
  },
  {
    "name": "16.webp",
    "src": "stickers/KUNgal4/16.webp"
  },
  {
    "name": "17.webp",
    "src": "stickers/KUNgal4/17.webp"
  },
  {
    "name": "18.webp",
    "src": "stickers/KUNgal4/18.webp"
  },
  {
    "name": "19.webp",
    "src": "stickers/KUNgal4/19.webp"
  },
  {
    "name": "2.webp",
    "src": "stickers/KUNgal4/2.webp"
  },
  {
    "name": "20.webp",
    "src": "stickers/KUNgal4/20.webp"
  },
  {
    "name": "21.webp",
    "src": "stickers/KUNgal4/21.webp"
  },
  {
    "name": "22.webp",
    "src": "stickers/KUNgal4/22.webp"
  },
  {
    "name": "23.webp",
    "src": "stickers/KUNgal4/23.webp"
  },
  {
    "name": "24.webp",
    "src": "stickers/KUNgal4/24.webp"
  },
  {
    "name": "25.webp",
    "src": "stickers/KUNgal4/25.webp"
  },
  {
    "name": "26.webp",
    "src": "stickers/KUNgal4/26.webp"
  },
  {
    "name": "27.webp",
    "src": "stickers/KUNgal4/27.webp"
  },
  {
    "name": "28.webp",
    "src": "stickers/KUNgal4/28.webp"
  },
  {
    "name": "29.webp",
    "src": "stickers/KUNgal4/29.webp"
  },
  {
    "name": "3.webp",
    "src": "stickers/KUNgal4/3.webp"
  },
  {
    "name": "30.webp",
    "src": "stickers/KUNgal4/30.webp"
  },
  {
    "name": "31.webp",
    "src": "stickers/KUNgal4/31.webp"
  },
  {
    "name": "32.webp",
    "src": "stickers/KUNgal4/32.webp"
  },
  {
    "name": "33.webp",
    "src": "stickers/KUNgal4/33.webp"
  },
  {
    "name": "34.webp",
    "src": "stickers/KUNgal4/34.webp"
  },
  {
    "name": "35.webp",
    "src": "stickers/KUNgal4/35.webp"
  },
  {
    "name": "36.webp",
    "src": "stickers/KUNgal4/36.webp"
  },
  {
    "name": "37.webp",
    "src": "stickers/KUNgal4/37.webp"
  },
  {
    "name": "38.webp",
    "src": "stickers/KUNgal4/38.webp"
  },
  {
    "name": "39.webp",
    "src": "stickers/KUNgal4/39.webp"
  },
  {
    "name": "4.webp",
    "src": "stickers/KUNgal4/4.webp"
  },
  {
    "name": "40.webp",
    "src": "stickers/KUNgal4/40.webp"
  },
  {
    "name": "41.webp",
    "src": "stickers/KUNgal4/41.webp"
  },
  {
    "name": "42.webp",
    "src": "stickers/KUNgal4/42.webp"
  },
  {
    "name": "43.webp",
    "src": "stickers/KUNgal4/43.webp"
  },
  {
    "name": "44.webp",
    "src": "stickers/KUNgal4/44.webp"
  },
  {
    "name": "45.webp",
    "src": "stickers/KUNgal4/45.webp"
  },
  {
    "name": "46.webp",
    "src": "stickers/KUNgal4/46.webp"
  },
  {
    "name": "47.webp",
    "src": "stickers/KUNgal4/47.webp"
  },
  {
    "name": "48.webp",
    "src": "stickers/KUNgal4/48.webp"
  },
  {
    "name": "49.webp",
    "src": "stickers/KUNgal4/49.webp"
  },
  {
    "name": "5.webp",
    "src": "stickers/KUNgal4/5.webp"
  },
  {
    "name": "50.webp",
    "src": "stickers/KUNgal4/50.webp"
  },
  {
    "name": "51.webp",
    "src": "stickers/KUNgal4/51.webp"
  },
  {
    "name": "52.webp",
    "src": "stickers/KUNgal4/52.webp"
  },
  {
    "name": "53.webp",
    "src": "stickers/KUNgal4/53.webp"
  },
  {
    "name": "54.webp",
    "src": "stickers/KUNgal4/54.webp"
  },
  {
    "name": "55.webp",
    "src": "stickers/KUNgal4/55.webp"
  },
  {
    "name": "56.webp",
    "src": "stickers/KUNgal4/56.webp"
  },
  {
    "name": "57.webp",
    "src": "stickers/KUNgal4/57.webp"
  },
  {
    "name": "58.webp",
    "src": "stickers/KUNgal4/58.webp"
  },
  {
    "name": "59.webp",
    "src": "stickers/KUNgal4/59.webp"
  },
  {
    "name": "6.webp",
    "src": "stickers/KUNgal4/6.webp"
  },
  {
    "name": "60.webp",
    "src": "stickers/KUNgal4/60.webp"
  },
  {
    "name": "61.webp",
    "src": "stickers/KUNgal4/61.webp"
  },
  {
    "name": "62.webp",
    "src": "stickers/KUNgal4/62.webp"
  },
  {
    "name": "63.webp",
    "src": "stickers/KUNgal4/63.webp"
  },
  {
    "name": "64.webp",
    "src": "stickers/KUNgal4/64.webp"
  },
  {
    "name": "65.webp",
    "src": "stickers/KUNgal4/65.webp"
  },
  {
    "name": "66.webp",
    "src": "stickers/KUNgal4/66.webp"
  },
  {
    "name": "67.webp",
    "src": "stickers/KUNgal4/67.webp"
  },
  {
    "name": "68.webp",
    "src": "stickers/KUNgal4/68.webp"
  },
  {
    "name": "69.webp",
    "src": "stickers/KUNgal4/69.webp"
  },
  {
    "name": "7.webp",
    "src": "stickers/KUNgal4/7.webp"
  },
  {
    "name": "70.webp",
    "src": "stickers/KUNgal4/70.webp"
  },
  {
    "name": "71.webp",
    "src": "stickers/KUNgal4/71.webp"
  },
  {
    "name": "72.webp",
    "src": "stickers/KUNgal4/72.webp"
  },
  {
    "name": "73.webp",
    "src": "stickers/KUNgal4/73.webp"
  },
  {
    "name": "74.webp",
    "src": "stickers/KUNgal4/74.webp"
  },
  {
    "name": "75.webp",
    "src": "stickers/KUNgal4/75.webp"
  },
  {
    "name": "76.webp",
    "src": "stickers/KUNgal4/76.webp"
  },
  {
    "name": "77.webp",
    "src": "stickers/KUNgal4/77.webp"
  },
  {
    "name": "78.webp",
    "src": "stickers/KUNgal4/78.webp"
  },
  {
    "name": "79.webp",
    "src": "stickers/KUNgal4/79.webp"
  },
  {
    "name": "8.webp",
    "src": "stickers/KUNgal4/8.webp"
  },
  {
    "name": "80.webp",
    "src": "stickers/KUNgal4/80.webp"
  },
  {
    "name": "9.webp",
    "src": "stickers/KUNgal4/9.webp"
  }
]